sqlite_vfs/__init__.py
sqlite_vfs/core.py
sqlite_vfs/folder_packer.py
sqlite_vfs/folder_unpacker.py
sqlite_vfs/cli/__init__.py
sqlite_vfs/cli/packer.py
sqlite_vfs/cli/unpacker.py
sqlite_vfs-0.1.0.dist-info/METADATA
sqlite_vfs-0.1.0.dist-info/WHEEL
sqlite_vfs-0.1.0.dist-info/entry_points.txt
sqlite_vfs-0.1.0.dist-info/RECORD
