Metadata-Version: 2.4
Name: sqlite-vfs
Version: 0.1.0
Summary: sqlite virtual file system
Requires-Python: >=3.7
